ssh_deployer/__init__.py
ssh_deployer/builder.py
ssh_deployer/connection.py
ssh_deployer/executor.py
ssh_deployer/manager.py
ssh_bearacer-1.0.1.dist-info/LICENSE
ssh_bearacer-1.0.1.dist-info/METADATA
ssh_bearacer-1.0.1.dist-info/WHEEL
ssh_bearacer-1.0.1.dist-info/entry_points.txt
ssh_bearacer-1.0.1.dist-info/top_level.txt
ssh_bearacer-1.0.1.dist-info/RECORD
